sptk/__init__.py
sptk/config.py
sptk/envi_sli_formatter.py
sptk/instrument.py
sptk/linear_discriminant_analysis.py
sptk/material_collection.py
sptk/material_sets.py
sptk/observation.py
sptk/pds_relab_formatter.py
sptk/spectral_library_analyser.py
sptk/spectral_parameter_combination_classifier.py
sptk/spectral_parameters.py
sptk-0.1.dist-info/LICENSE.md
sptk-0.1.dist-info/METADATA
sptk-0.1.dist-info/WHEEL
sptk-0.1.dist-info/RECORD
