Metadata-Version: 2.1
Name: sptk
Version: 0.1
Summary: The Spectral Parameters Toolkit (SPTK) is a Python package for investigating the ability of a multispectral imaging system to identify distinct materials and material groups through differences in reflectance spectra.
Home-page: https://github.com/rbstabbins/sptk
License: MIT
Keywords: reflectance,spectroscopy,spectral imaging,planetary surfaces,remote sensing,spectral parameters
Author: Roger Stabbins
Author-email: r.stabbins@nhm.ac.uk
Maintainer: Roger Stabbins
Maintainer-email: r.stabbins@nhm.ac.uk
Requires-Python: >=3.10.8,<4.0.0
Classifier: Development Status :: 3 - Alpha
Classifier: Intended Audience :: Science/Research
Classifier: License :: OSI Approved :: MIT License
Classifier: Programming Language :: Python :: 3
Classifier: Programming Language :: Python :: 3.11
Classifier: Programming Language :: Python :: 3.12
Classifier: Programming Language :: Python :: 3.10
Classifier: Topic :: Scientific/Engineering :: Astronomy
Requires-Dist: click (==8.1)
Requires-Dist: ipykernel (>=6.17.0,<7.0.0)
Requires-Dist: matplotlib (==3.6.2)
Requires-Dist: numpy (==1.23.5)
Requires-Dist: pandas (==1.5.2)
Requires-Dist: pillow (==9.3.0)
Requires-Dist: pysptools (==0.15.0)
Requires-Dist: scikit-learn (==1.1.3)
Requires-Dist: scipy (==1.9.3)
Requires-Dist: seaborn (==0.12.2)
Requires-Dist: statsmodels (==0.13.2)
Requires-Dist: tabulate (==0.8.10)
Requires-Dist: toml (>=0.10.2,<0.11.0)
Project-URL: Repository, https://github.com/rbstabbins/sptk
